hrcx/__init__.py
hrcx/__main__.py
hrcx/api.py
hrcx/cli.py
hrcx/interactive.py
hrcx/py.typed
hrcx/crypto/__init__.py
hrcx/crypto/encryption.py
hrcx/horcrux/__init__.py
hrcx/horcrux/format.py
hrcx/shamir/__init__.py
hrcx/shamir/shamir.py
hrcx/shamir/tables.py
hrcx-1.2.4.dist-info/licenses/LICENSE
hrcx-1.2.4.dist-info/METADATA
hrcx-1.2.4.dist-info/WHEEL
hrcx-1.2.4.dist-info/entry_points.txt
hrcx-1.2.4.dist-info/top_level.txt
hrcx-1.2.4.dist-info/RECORD
