Metadata-Version: 2.4
Name: hrcx
Version: 1.2.4
Summary: Split your files into encrypted fragments without needing all fragments for reconstruction!
Author-email: Julius Pleunes <jjgpleunes@gmail.com>
License: MIT
Project-URL: Homepage, https://github.com/juliuspleunes4/horcrux
Project-URL: Documentation, https://github.com/juliuspleunes4/horcrux#readme
Project-URL: Repository, https://github.com/juliuspleunes4/horcrux
Project-URL: Issues, https://github.com/juliuspleunes4/horcrux/issues
Project-URL: Changelog, https://github.com/juliuspleunes4/horcrux/blob/master/docs/CHANGELOG.md
Keywords: encryption,shamir,secret-sharing,security,cryptography,file-splitting,horcrux,threshold-cryptography,aes,cli
Classifier: Development Status :: 4 - Beta
Classifier: Intended Audience :: Developers
Classifier: Intended Audience :: System Administrators
Classifier: License :: OSI Approved :: MIT License
Classifier: Operating System :: OS Independent
Classifier: Programming Language :: Python :: 3
Classifier: Programming Language :: Python :: 3.8
Classifier: Programming Language :: Python :: 3.9
Classifier: Programming Language :: Python :: 3.10
Classifier: Programming Language :: Python :: 3.11
Classifier: Programming Language :: Python :: 3.12
Classifier: Topic :: Security :: Cryptography
Classifier: Topic :: System :: Archiving :: Backup
Classifier: Topic :: Utilities
Requires-Python: >=3.8
License-File: LICENSE
Requires-Dist: cryptography>=41.0.0
Requires-Dist: click>=8.0.0
Provides-Extra: dev
Requires-Dist: pytest>=7.0.0; extra == "dev"
Requires-Dist: pytest-cov>=4.0.0; extra == "dev"
Requires-Dist: black>=23.0.0; extra == "dev"
Requires-Dist: ruff>=0.1.0; extra == "dev"
Requires-Dist: mypy>=1.0.0; extra == "dev"
Dynamic: license-file
